LICENSE
MANIFEST.in
README.md
setup.py
karateclub/__init__.py
karateclub/estimator.py
karateclub/version.py
karateclub.egg-info/PKG-INFO
karateclub.egg-info/SOURCES.txt
karateclub.egg-info/dependency_links.txt
karateclub.egg-info/requires.txt
karateclub.egg-info/top_level.txt
karateclub/community_detection/__init__.py
karateclub/community_detection/non_overlapping/__init__.py
karateclub/community_detection/non_overlapping/edmot.py
karateclub/community_detection/non_overlapping/gemsec.py
karateclub/community_detection/non_overlapping/label_propagation.py
karateclub/community_detection/non_overlapping/scd.py
karateclub/community_detection/overlapping/__init__.py
karateclub/community_detection/overlapping/bigclam.py
karateclub/community_detection/overlapping/danmf.py
karateclub/community_detection/overlapping/ego_splitter.py
karateclub/community_detection/overlapping/mnmf.py
karateclub/community_detection/overlapping/nnsed.py
karateclub/community_detection/overlapping/symmnmf.py
karateclub/dataset/__init__.py
karateclub/dataset/dataset_reader.py
karateclub/graph_embedding/__init__.py
karateclub/graph_embedding/feathergraph.py
karateclub/graph_embedding/fgsd.py
karateclub/graph_embedding/geoscattering.py
karateclub/graph_embedding/gl2vec.py
karateclub/graph_embedding/graph2vec.py
karateclub/graph_embedding/ige.py
karateclub/graph_embedding/ldp.py
karateclub/graph_embedding/netlsd.py
karateclub/graph_embedding/sf.py
karateclub/graph_embedding/waveletcharacteristic.py
karateclub/node_embedding/__init__.py
karateclub/node_embedding/attributed/__init__.py
karateclub/node_embedding/attributed/ae.py
karateclub/node_embedding/attributed/asne.py
karateclub/node_embedding/attributed/bane.py
karateclub/node_embedding/attributed/feathernode.py
karateclub/node_embedding/attributed/fscnmf.py
karateclub/node_embedding/attributed/musae.py
karateclub/node_embedding/attributed/sine.py
karateclub/node_embedding/attributed/tadw.py
karateclub/node_embedding/attributed/tene.py
karateclub/node_embedding/meta/__init__.py
karateclub/node_embedding/meta/neu.py
karateclub/node_embedding/neighbourhood/__init__.py
