Metadata-Version: 1.1
Name: karateclub
Version: 1.3.3
Summary: A general purpose library for community detection, network embedding, and graph mining research.
Home-page: https://github.com/benedekrozemberczki/karateclub
Author: Benedek Rozemberczki
Author-email: benedek.rozemberczki@gmail.com
License: GPLv3
Download-URL: https://github.com/benedekrozemberczki/karateclub/archive/v_10303.tar.gz
Keywords: community,detection,networkx,graph,clustering,embedding,deepwalk,graph2vec,node2vec,deep,node-embedding,graph-embedding,learning,louvain,machine-learning,deep-learning,deeplearning
Platform: UNKNOWN
Classifier: Development Status :: 3 - Alpha
Classifier: Intended Audience :: Developers
Classifier: Topic :: Software Development :: Build Tools
Classifier: License :: OSI Approved :: MIT License
Classifier: Programming Language :: Python :: 3.7
